LICENSE
MANIFEST.in
README.md
setup.py
bin/__init__.py
bin/main.py
common/__init__.py
common/ai.py
qinglink.egg-info/PKG-INFO
qinglink.egg-info/SOURCES.txt
qinglink.egg-info/dependency_links.txt
qinglink.egg-info/entry_points.txt
qinglink.egg-info/requires.txt
qinglink.egg-info/top_level.txt