Metadata-Version: 2.2
Name: qinglink
Version: 0.0.1
Summary: The toolset for link project
Home-page: https://github.com/Alndaly/qinglink
Author: Kinda Hall
Author-email: 1142704468@qq.com
Maintainer: Kinda Hall
Maintainer-email: 1142704468@qq.com
License: Copyright (c) 2024 Kinda Hall
Keywords: pip,tools
Platform: any
Requires-Python: >=3.10
License-File: LICENSE
Requires-Dist: typer
Requires-Dist: httpx
Requires-Dist: tqdm
Requires-Dist: safetensors
Requires-Dist: torch
Requires-Dist: numpy
Requires-Dist: torchvision
Dynamic: author
Dynamic: author-email
Dynamic: description
Dynamic: description-content-type
Dynamic: home-page
Dynamic: keywords
Dynamic: license
Dynamic: maintainer
Dynamic: maintainer-email
Dynamic: platform
Dynamic: requires-dist
Dynamic: requires-python
Dynamic: summary
